cocof/__init__.py
cocof/cocof.py
cocof/filehandling.py
tests/__init__.py
tests/test_filehandling.py
cocof-1.0.0.dist-info/LICENSE
cocof-1.0.0.dist-info/METADATA
cocof-1.0.0.dist-info/WHEEL
cocof-1.0.0.dist-info/dependency_links.txt
cocof-1.0.0.dist-info/entry_points.txt
cocof-1.0.0.dist-info/top_level.txt
cocof-1.0.0.dist-info/RECORD
