Metadata-Version: 2.1
Name: cocof
Version: 1.0.0
Summary: Consistent CLI config file modifier
Home-page: https://github.com/astzweig/cocof-py
Author: Astzweig UG(haftungsbeschränkt) & Co. KG
Author-email: it@astzweig.de
License: UNKNOWN
Keywords: toml,yaml,json,terminal,cli,edit
Platform: UNKNOWN
Classifier: Development Status :: 4 - Beta
Classifier: Intended Audience :: Developers
Classifier: License :: OSI Approved :: European Union Public Licence 1.2 (EUPL 1.2)
Classifier: Topic :: Database
Classifier: Topic :: Terminals
Classifier: Topic :: Text Processing
Classifier: Topic :: Utilities
Classifier: Programming Language :: Python :: 3.6
Classifier: Operating System :: OS Independent
Requires-Dist: click (<8.0,>=7.0)
Requires-Dist: tomlkit (<1.0)
Requires-Dist: ruamel.yaml (<1.0)
Requires-Dist: jsonpatch (<2.0,>=1.23)
